gibram/__init__.py
gibram/_client.py
gibram/_connection.py
gibram/_protocol.py
gibram/_version.py
gibram/exceptions.py
gibram/indexer.py
gibram/py.typed
gibram/types.py
gibram/chunkers/__init__.py
gibram/chunkers/base.py
gibram/chunkers/token.py
gibram/embedders/__init__.py
gibram/embedders/base.py
gibram/embedders/openai.py
gibram/extractors/__init__.py
gibram/extractors/base.py
gibram/extractors/openai.py
gibram/proto/__init__.py
gibram/proto/gibram_pb2.py
gibram-0.2.0.dist-info/METADATA
gibram-0.2.0.dist-info/WHEEL
gibram-0.2.0.dist-info/top_level.txt
gibram-0.2.0.dist-info/RECORD
