Metadata-Version: 2.4
Name: gibram
Version: 0.2.0
Summary: GraphRAG-style Python SDK for GibRAM - Graph in-Buffer Retrieval & Associative Memory
Author-email: GibRAM Team <support@gibram.io>
Maintainer-email: GibRAM Team <support@gibram.io>
License: MIT
Project-URL: Homepage, https://github.com/gibram-io/gibram
Project-URL: Documentation, https://gibram.io/docs/python-sdk
Project-URL: Repository, https://github.com/gibram-io/gibram
Project-URL: Issues, https://github.com/gibram-io/gibram/issues
Keywords: rag,graphrag,graph,knowledge-graph,vector-search,llm,ai,embeddings,entity-extraction
Classifier: Development Status :: 4 - Beta
Classifier: Intended Audience :: Developers
Classifier: Intended Audience :: Science/Research
Classifier: License :: OSI Approved :: MIT License
Classifier: Operating System :: OS Independent
Classifier: Programming Language :: Python :: 3
Classifier: Programming Language :: Python :: 3.8
Classifier: Programming Language :: Python :: 3.9
Classifier: Programming Language :: Python :: 3.10
Classifier: Programming Language :: Python :: 3.11
Classifier: Programming Language :: Python :: 3.12
Classifier: Topic :: Scientific/Engineering :: Artificial Intelligence
Classifier: Topic :: Software Development :: Libraries :: Python Modules
Classifier: Typing :: Typed
Requires-Python: >=3.8
Requires-Dist: protobuf>=3.20.0
Requires-Dist: openai>=1.0.0
Requires-Dist: tqdm>=4.65.0
Provides-Extra: dev
Requires-Dist: pytest>=7.0.0; extra == "dev"
Requires-Dist: black>=23.0.0; extra == "dev"
Requires-Dist: ruff>=0.1.0; extra == "dev"
Provides-Extra: anthropic
Requires-Dist: anthropic>=0.18.0; extra == "anthropic"
